{
  "sourceRepository": "https://github.com/BytePioneer-AI/openclaw-china",
  "scope": "openclaw-china",
  "label": "downloads",
  "description": "Combined total of npm public registry and npmmirror totals.",
  "totalDownloads": 330215,
  "sources": [
    {
      "id": "npm",
      "registry": "npm public registry",
      "totalDownloads": 238530,
      "badgeFileBase": "npm-downloads-18m"
    },
    {
      "id": "npmmirror",
      "registry": "npmmirror",
      "totalDownloads": 91685,
      "badgeFileBase": "npmmirror-downloads-total"
    }
  ]
}
