{
  "sourceRepository": "https://github.com/BytePioneer-AI/openclaw-china",
  "scope": "openclaw-china",
  "registry": "npm public registry",
  "period": {
    "label": "npm public API longest window",
    "start": "2024-11-21",
    "end": "2026-05-21",
    "months": 18
  },
  "totalDownloads": 224142,
  "packages": [
    {
      "name": "@openclaw-china/channels",
      "downloads": 23623,
      "status": "ok",
      "period": {
        "start": "2024-11-21",
        "end": "2026-05-21"
      }
    },
    {
      "name": "@openclaw-china/dingtalk",
      "downloads": 27946,
      "status": "ok",
      "period": {
        "start": "2024-11-21",
        "end": "2026-05-21"
      }
    },
    {
      "name": "@openclaw-china/feishu-china",
      "downloads": 17707,
      "status": "ok",
      "period": {
        "start": "2024-11-21",
        "end": "2026-05-21"
      }
    },
    {
      "name": "@openclaw-china/qqbot",
      "downloads": 19071,
      "status": "ok",
      "period": {
        "start": "2024-11-21",
        "end": "2026-05-21"
      }
    },
    {
      "name": "@openclaw-china/shared",
      "downloads": 58833,
      "status": "ok",
      "period": {
        "start": "2024-11-21",
        "end": "2026-05-21"
      }
    },
    {
      "name": "@openclaw-china/wechat-mp",
      "downloads": 4167,
      "status": "ok",
      "period": {
        "start": "2024-11-21",
        "end": "2026-05-21"
      }
    },
    {
      "name": "@openclaw-china/wecom",
      "downloads": 40724,
      "status": "ok",
      "period": {
        "start": "2024-11-21",
        "end": "2026-05-21"
      }
    },
    {
      "name": "@openclaw-china/wecom-app",
      "downloads": 27140,
      "status": "ok",
      "period": {
        "start": "2024-11-21",
        "end": "2026-05-21"
      }
    },
    {
      "name": "@openclaw-china/wecom-kf",
      "downloads": 4931,
      "status": "ok",
      "period": {
        "start": "2024-11-21",
        "end": "2026-05-21"
      }
    }
  ],
  "unavailablePackages": []
}
