{
  "sourceRepository": "https://github.com/BytePioneer-AI/openclaw-china",
  "scope": "openclaw-china",
  "registry": "npmmirror",
  "period": {
    "label": "npmmirror historical total aggregated by yearly range API",
    "end": "2026-06-17",
    "rangeMode": "package created date -> current date, split by calendar year"
  },
  "totalDownloads": 90378,
  "packages": [
    {
      "name": "@openclaw-china/channels",
      "downloads": 7830,
      "status": "ok",
      "createdAt": "2026-01-30T05:37:34.674Z",
      "period": {
        "start": "2026-01-30",
        "end": "2026-06-17"
      },
      "yearlyRanges": [
        {
          "start": "2026-01-30",
          "end": "2026-06-17",
          "downloads": 7830
        }
      ]
    },
    {
      "name": "@openclaw-china/dingtalk",
      "downloads": 12789,
      "status": "ok",
      "createdAt": "2026-01-30T05:31:27.109Z",
      "period": {
        "start": "2026-01-30",
        "end": "2026-06-17"
      },
      "yearlyRanges": [
        {
          "start": "2026-01-30",
          "end": "2026-06-17",
          "downloads": 12789
        }
      ]
    },
    {
      "name": "@openclaw-china/feishu-china",
      "downloads": 7066,
      "status": "ok",
      "createdAt": "2026-02-08T11:04:21.987Z",
      "period": {
        "start": "2026-02-08",
        "end": "2026-06-17"
      },
      "yearlyRanges": [
        {
          "start": "2026-02-08",
          "end": "2026-06-17",
          "downloads": 7066
        }
      ]
    },
    {
      "name": "@openclaw-china/qqbot",
      "downloads": 8981,
      "status": "ok",
      "createdAt": "2026-02-06T06:31:54.761Z",
      "period": {
        "start": "2026-02-06",
        "end": "2026-06-17"
      },
      "yearlyRanges": [
        {
          "start": "2026-02-06",
          "end": "2026-06-17",
          "downloads": 8981
        }
      ]
    },
    {
      "name": "@openclaw-china/shared",
      "downloads": 24713,
      "status": "ok",
      "createdAt": "2026-01-30T05:30:19.337Z",
      "period": {
        "start": "2026-01-30",
        "end": "2026-06-17"
      },
      "yearlyRanges": [
        {
          "start": "2026-01-30",
          "end": "2026-06-17",
          "downloads": 24713
        }
      ]
    },
    {
      "name": "@openclaw-china/wechat-mp",
      "downloads": 2062,
      "status": "ok",
      "createdAt": "2026-03-20T16:40:15.695Z",
      "period": {
        "start": "2026-03-20",
        "end": "2026-06-17"
      },
      "yearlyRanges": [
        {
          "start": "2026-03-20",
          "end": "2026-06-17",
          "downloads": 2062
        }
      ]
    },
    {
      "name": "@openclaw-china/wecom",
      "downloads": 13833,
      "status": "ok",
      "createdAt": "2026-01-30T11:50:49.176Z",
      "period": {
        "start": "2026-01-30",
        "end": "2026-06-17"
      },
      "yearlyRanges": [
        {
          "start": "2026-01-30",
          "end": "2026-06-17",
          "downloads": 13833
        }
      ]
    },
    {
      "name": "@openclaw-china/wecom-app",
      "downloads": 11022,
      "status": "ok",
      "createdAt": "2026-02-04T16:05:59.811Z",
      "period": {
        "start": "2026-02-04",
        "end": "2026-06-17"
      },
      "yearlyRanges": [
        {
          "start": "2026-02-04",
          "end": "2026-06-17",
          "downloads": 11022
        }
      ]
    },
    {
      "name": "@openclaw-china/wecom-kf",
      "downloads": 2082,
      "status": "ok",
      "createdAt": "2026-03-17T16:14:42.837Z",
      "period": {
        "start": "2026-03-17",
        "end": "2026-06-17"
      },
      "yearlyRanges": [
        {
          "start": "2026-03-17",
          "end": "2026-06-17",
          "downloads": 2082
        }
      ]
    }
  ],
  "unavailablePackages": []
}
